i2cx/__init__.py
i2cx/core/MessageBox.py
i2cx/core/ProgressDialog.py
i2cx/core/Worker.py
i2cx/core/WorkerSignals.py
i2cx/core/__init__.py
i2cx/core/assets/coming_soon.png
i2cx/core/assets/logo_cyber_range.png
i2cx/core/assets/logo_linux_platform.png
i2cx/core/assets/logo_platform.png
i2cx/core/assets/logo_scanner.png
i2cx/core/assets/logo_scanner_lite.png
i2cx/core/gui/gui.ui
i2cx/core/gui/theme.xml
i2cx/plugins/__init__.py
i2cx/plugins/i2c/__init__.py
i2cx/plugins/i2c/i2cErase.py
i2cx/plugins/i2c/i2cReadToDataview.py
i2cx/plugins/i2c/i2cReadToFile.py
i2cx/plugins/i2c/i2cScan.py
i2cx/plugins/i2c/i2cWriteFromDataview.py
i2cx/plugins/i2c/i2cWriteFromFile.py
i2cx/plugins/i2c/gui/gui.ui
i2cx/plugins/spi/__init__.py
i2cx/plugins/spi/spiErase.py
i2cx/plugins/spi/spiGetExtendedID.py
i2cx/plugins/spi/spiGetID.py
i2cx/plugins/spi/spiReadToFile.py
i2cx/plugins/spi/spiWriteFromFile.py
i2cx/plugins/spi/gui/gui.ui
i2cx/plugins/uart/__init__.py
i2cx/plugins/uart/gui/gui.ui
i2cx-0.9.3.dist-info/LICENSE
i2cx-0.9.3.dist-info/METADATA
i2cx-0.9.3.dist-info/WHEEL
i2cx-0.9.3.dist-info/entry_points.txt
i2cx-0.9.3.dist-info/top_level.txt
i2cx-0.9.3.dist-info/RECORD
