Metadata-Version: 2.1
Name: i2cx
Version: 0.9.3
Summary: Graphical interface for I2Cx Cyber Range, scanner-Lite(FT2232H),scanner (FPGA) and platform (stm32F7) 
Home-page: https://github.com/I2Cx-Cyber-Range/i2cx-gui
Author: LOOTUS
Author-email: julien.moinard@lootus.net
License: UNKNOWN
Project-URL: Homepage, https://www.i2cx.io
Keywords: ftdi i2cx pyside cyberrange IoT stm32 fpga lattice
Platform: UNKNOWN
Classifier: Programming Language :: Python :: 3
Classifier: License :: OSI Approved :: GNU General Public License v3 (GPLv3)
Classifier: Operating System :: OS Independent
Requires-Python: >=3.6
License-File: LICENSE
Requires-Dist: pyside6
Requires-Dist: pyftdi
